snapper/.DS_Store
snapper/__init__.py
snapper/api_views.py
snapper/cli.py
snapper/config.yaml
snapper/ghostdriver.log
snapper/googleExample.txt
snapper/task.py
snapper/worker.py
snapper/__pycache__/__init__.cpython-37.pyc
snapper/__pycache__/api_views.cpython-37.pyc
snapper/__pycache__/cli.cpython-37.pyc
snapper/__pycache__/snapper.cpython-37.pyc
snapper/__pycache__/task.cpython-37.pyc
snapper/__pycache__/worker.cpython-37.pyc
snapper/templates/.DS_Store
snapper/templates/index.html
snapper/templates/css/materialize.min.css
snapper/templates/js/jquery.min.js
snapper/templates/js/materialize.min.js
snapper-0.0.10.data/data/snapper/config.yaml
snapper-0.0.10.dist-info/LICENSE
snapper-0.0.10.dist-info/METADATA
snapper-0.0.10.dist-info/WHEEL
snapper-0.0.10.dist-info/entry_points.txt
snapper-0.0.10.dist-info/top_level.txt
snapper-0.0.10.dist-info/RECORD
