Metadata-Version: 2.1
Name: snapper
Version: 0.0.10
Summary: A security tool for grabbing screenshots of many web                      hosts.
Home-page: UNKNOWN
License: UNKNOWN
Platform: UNKNOWN
Classifier: Programming Language :: Python :: 3
Classifier: License :: OSI Approved :: MIT License
Classifier: Operating System :: OS Independent
Requires-Dist: flask (==1.1.1)
Requires-Dist: flask-restful (==0.3.7)
Requires-Dist: Jinja2 (==2.10.1)
Requires-Dist: pyyaml
Requires-Dist: requests (==2.22.0)
Requires-Dist: selenium (==3.141.0)
Requires-Dist: urllib3 (==1.25.3)
